{"name":"build-javascript","namedChunkGroups":{"polyfill":{"name":"polyfill","assets":[{"name":"webpack-runtime-7df6fdca14433eb1029b.js","size":4104},{"name":"polyfill-de4dd29288f15cdded46.js","size":85856}],"filteredAssets":0,"assetsSize":89960,"filteredAuxiliaryAssets":2,"auxiliaryAssetsSize":224060},"app":{"name":"app","assets":[{"name":"webpack-runtime-7df6fdca14433eb1029b.js","size":4104},{"name":"framework-914ab7dcb0afa4946556.js","size":129769},{"name":"styles.ee48aaec3256a36589df.css","size":8892},{"name":"app-c7e994b5c387edb5270d.js","size":71446}],"filteredAssets":0,"assetsSize":214211,"filteredAuxiliaryAssets":3,"auxiliaryAssetsSize":666482},"component---src-pages-404-js":{"name":"component---src-pages-404-js","assets":[{"name":"commons-3b48306964d9fc096c07.js","size":23205},{"name":"component---src-pages-404-js-7497e13acc1ca977c372.js","size":652}],"filteredAssets":0,"assetsSize":23857,"filteredAuxiliaryAssets":2,"auxiliaryAssetsSize":77673},"component---src-pages-index-js":{"name":"component---src-pages-index-js","assets":[{"name":"commons-3b48306964d9fc096c07.js","size":23205},{"name":"component---src-pages-index-js-597ae6a6aa8b0e95c15e.js","size":997}],"filteredAssets":0,"assetsSize":24202,"filteredAuxiliaryAssets":2,"auxiliaryAssetsSize":78032},"component---src-pages-jobs-js":{"name":"component---src-pages-jobs-js","assets":[{"name":"commons-3b48306964d9fc096c07.js","size":23205},{"name":"component---src-pages-jobs-js-022ad79c80b975229dcc.js","size":464}],"filteredAssets":0,"assetsSize":23669,"filteredAuxiliaryAssets":2,"auxiliaryAssetsSize":77414},"component---src-pages-projects-js":{"name":"component---src-pages-projects-js","assets":[{"name":"commons-3b48306964d9fc096c07.js","size":23205},{"name":"component---src-pages-projects-js-6957683b2958b451cbd1.js","size":17339}],"filteredAssets":0,"assetsSize":40544,"filteredAuxiliaryAssets":5,"auxiliaryAssetsSize":150507},"component---src-pages-team-js":{"name":"component---src-pages-team-js","assets":[{"name":"commons-3b48306964d9fc096c07.js","size":23205},{"name":"component---src-pages-team-js-a4e1054953b9d0640547.js","size":1978}],"filteredAssets":0,"assetsSize":25183,"filteredAuxiliaryAssets":7,"auxiliaryAssetsSize":200291}},"assetsByChunkName":{"polyfill":["webpack-runtime-7df6fdca14433eb1029b.js","polyfill-de4dd29288f15cdded46.js"],"app":["webpack-runtime-7df6fdca14433eb1029b.js","framework-914ab7dcb0afa4946556.js","styles.ee48aaec3256a36589df.css","app-c7e994b5c387edb5270d.js"],"component---src-pages-404-js":["commons-3b48306964d9fc096c07.js","component---src-pages-404-js-7497e13acc1ca977c372.js"],"component---src-pages-index-js":["commons-3b48306964d9fc096c07.js","component---src-pages-index-js-597ae6a6aa8b0e95c15e.js"],"component---src-pages-jobs-js":["commons-3b48306964d9fc096c07.js","component---src-pages-jobs-js-022ad79c80b975229dcc.js"],"component---src-pages-projects-js":["commons-3b48306964d9fc096c07.js","component---src-pages-projects-js-6957683b2958b451cbd1.js"],"component---src-pages-team-js":["commons-3b48306964d9fc096c07.js","component---src-pages-team-js-a4e1054953b9d0640547.js"]},"childAssetsByChunkName":{}}